pyai_abalone/__init__.py
pyai_abalone/abalone_ai.py
pyai_abalone/board.py
pyai_abalone/board_ai.py
pyai_abalone/constants.py
pyai_abalone/display.py
pyai_abalone/game_ai.py
pyai_abalone/model_ai.py
pyai_abalone/player_ai.py
pyai_abalone/starting_positions.py
pyai_abalone/ai_files/moves2idx-red-permutated.json
pyai_abalone/ai_files/mz-weights.h5
pyai_abalone/images/marble_blue.png
pyai_abalone/images/marble_empty.png
pyai_abalone/images/marble_green.png
pyai_abalone/images/marble_purple.png
pyai_abalone/images/marble_red.png
pyai_abalone/images/marble_yellow.png
pyai_abalone/images/skull.png
pyai_abalone-1.0.2.dist-info/METADATA
pyai_abalone-1.0.2.dist-info/WHEEL
pyai_abalone-1.0.2.dist-info/top_level.txt
pyai_abalone-1.0.2.dist-info/RECORD
