Metadata-Version: 2.1
Name: pyai-abalone
Version: 1.0.2
Summary: AI abalone player based on Alpha-Zero's concept with GUI
Home-page: https://github.com/harloc-AI/pyai_abalone
Author: Harald Locke
Author-email: haraldlocke@gmx.de
Project-URL: Source Code, https://github.com/harloc-AI/pyai_abalone
Classifier: Programming Language :: Python :: 3
Classifier: License :: OSI Approved :: MIT License
Classifier: Operating System :: OS Independent
Requires-Python: >=3.11
Requires-Dist: tensorflow==2.12
Requires-Dist: numpy
Requires-Dist: pygame
Requires-Dist: colorama
